pynbs.py
pynbs-0.5.0.dist-info/LICENSE
pynbs-0.5.0.dist-info/METADATA
pynbs-0.5.0.dist-info/WHEEL
pynbs-0.5.0.dist-info/top_level.txt
pynbs-0.5.0.dist-info/RECORD
