Metadata-Version: 2.1
Name: pynbs
Version: 0.5.0
Summary: A simple python library to read and write .nbs files from Note Block Studio
Home-page: https://github.com/OpenNBS/pynbs
Author: Valentin Berlier
Author-email: berlier.v@gmail.com
License: MIT
Keywords: note-block-studio minecraft nbs-files
Platform: any
Classifier: Development Status :: 4 - Beta
Classifier: Intended Audience :: Developers
Classifier: Topic :: Software Development :: Libraries :: Python Modules
Classifier: License :: OSI Approved :: MIT License
Classifier: Operating System :: OS Independent
Classifier: Programming Language :: Python :: 2
Classifier: Programming Language :: Python :: 2.7
Classifier: Programming Language :: Python :: 3
Classifier: Programming Language :: Python :: 3.6
Classifier: Programming Language :: Python :: 3.7
Classifier: Programming Language :: Python :: 3.8
Classifier: Programming Language :: Python :: 3.9
Requires-Python: >=2.7
License-File: LICENSE
